rediscache/__init__.py
rediscache/py.typed
rediscache/tools.py
rediscache-1.2.0.dist-info/METADATA
rediscache-1.2.0.dist-info/WHEEL
rediscache-1.2.0.dist-info/entry_points.txt
rediscache-1.2.0.dist-info/licenses/LICENSE
rediscache-1.2.0.dist-info/RECORD
