Metadata-Version: 2.4
Name: rediscache
Version: 1.2.0
Summary: Redis caching of functions evolving over time
License: MIT
License-File: LICENSE
Keywords: redis,performance,cache
Author: Pierre Cart-Grandjean
Author-email: pcart-grandjean@amadeus.com
Maintainer: Amadeus IT Group
Maintainer-email: opensource@amadeus.com
Requires-Python: >=3.11,<4.0
Classifier: Development Status :: 5 - Production/Stable
Classifier: Intended Audience :: Developers
Classifier: License :: OSI Approved :: MIT License
Classifier: Natural Language :: English
Classifier: Operating System :: OS Independent
Classifier: Programming Language :: Python :: 3
Classifier: Programming Language :: Python :: 3.11
Classifier: Programming Language :: Python :: 3.12
Classifier: Programming Language :: Python :: 3.13
Classifier: Programming Language :: Python :: 3.14
Classifier: Programming Language :: Python :: 3.10
Classifier: Programming Language :: Python :: 3.9
Classifier: Topic :: Software Development :: Libraries :: Python Modules
Requires-Dist: executiontime (==0.4.4)
Requires-Dist: redis (>=7.1.0,<8.0.0)
Project-URL: Repository, https://github.com/AmadeusITGroup/RedisCache
